pyconcept.cpython-312-x86_64-linux-gnu.so
tests/__init__.py
tests/testBinding.py
pyconcept-0.1.12.dist-info/WHEEL
pyconcept-0.1.12.dist-info/top_level.txt
pyconcept-0.1.12.dist-info/METADATA
pyconcept-0.1.12.dist-info/LICENSE
pyconcept-0.1.12.dist-info/RECORD
