Metadata-Version: 2.1
Name: pyconcept
Version: 0.1.12
Summary: Concept core Python wrapper
Author: CIHT CONCEPT, IRBorisov
Author-email: iborisov@acconcept.ru
License: MIT
Project-URL: GitHub, https://github.com/IRBorisov/ConceptCore/tree/main/pyconcept
Project-URL: Changelog, https://github.com/IRBorisov/ConceptCore/tree/main/pyconcept/CHANGELOG.md
Classifier: Development Status :: 3 - Alpha
Classifier: Intended Audience :: Developers
Classifier: Intended Audience :: Science/Research
Classifier: License :: OSI Approved :: MIT License
Classifier: Programming Language :: Python
Classifier: Programming Language :: Python :: 3
Classifier: Programming Language :: Python :: 3.12
Classifier: Topic :: Software Development :: Libraries :: Python Modules
License-File: LICENSE
